{
  "AllowMultiple": "false",
  "Description": "\"Make the folder selection button highly visible with a glowing green style and update its text to remove saving action references, completely aligning with the split folder configuration workflow.\"",
  "EndLine": "2197",
  "Instruction": "\"Make the folder selection button an ultra-glowing neon green button and update the text labels to be clean folder picker text without any saving references.\"",
  "ReplacementContent": "\"                          {/* Folder Selector Button: Ultra-Glowing Neon Green Style */}\\n                          <button\\n                            type=\\\"button\\\"\\n                            onClick={async () => {\\n                              try {\\n                                const dirHandle = await (window as any).showDirectoryPicker({ mode: 'readwrite' });\\n                                setExportDirHandle(dirHandle);\\n                                setExportFolderName(dirHandle.name);\\n                                localStorage.setItem('canvas_export_folder_name', dirHandle.name);\\n                              } catch (e: any) {\\n                                if (e.name === 'AbortError') return;\\n                                console.error('Folder picker error:', e);\\n                                alert('❌ ไม่สามารถเลือกโฟลเดอร์ได้: ' + e.message);\\n                              }\\n                            }}\\n                            className={`w-full py-3.5 px-4 rounded-xl border-2 text-xs font-black flex items-center justify-center gap-2.5 transition-all duration-300 active:scale-[0.97] hover:scale-[1.015] ${\\n                              exportFolderName\\n                                ? 'bg-gradient-to-r from-green-400 via-emerald-400 to-green-500 text-slate-950 border-green-300 shadow-[0_0_25px_rgba(34,197,94,0.65)] hover:shadow-[0_0_35px_rgba(34,197,94,0.85)]'\\n                                : 'bg-green-500/10 hover:bg-green-500/20 text-green-400 border-green-400/80 shadow-[0_0_18px_rgba(34,197,94,0.35)] hover:shadow-[0_0_28px_rgba(34,197,94,0.6)]'\\n                            }`}\\n                          >\\n                            <FolderOpen className={`w-4 h-4 shrink-0 ${exportFolderName ? 'text-slate-950' : 'text-green-400 animate-pulse'}`} />\\n                            <span>\\n                              {exportFolderName \\n                                ? `📁 โฟลเดอร์ปลายท\n<truncated 235 bytes>",
  "StartLine": "2169",
  "TargetContent": "\"                          {/* Folder Selector Button: Glowing Green Style */}\\n                          <button\\n                            type=\\\"button\\\"\\n                            onClick={async () => {\\n                              try {\\n                                const dirHandle = await (window as any).showDirectoryPicker({ mode: 'readwrite' });\\n                                setExportDirHandle(dirHandle);\\n                                setExportFolderName(dirHandle.name);\\n                                localStorage.setItem('canvas_export_folder_name', dirHandle.name);\\n                              } catch (e: any) {\\n                                if (e.name === 'AbortError') return;\\n                                console.error('Folder picker error:', e);\\n                                alert('❌ ไม่สามารถเลือกโฟลเดอร์ได้: ' + e.message);\\n                              }\\n                            }}\\n                            className={`w-full py-3 px-3 rounded-lg border text-xs font-black flex items-center justify-center gap-2 transition-all active:scale-[0.98] ${\\n                              exportFolderName\\n                                ? 'bg-emerald-500/20 text-emerald-300 border-emerald-500/40 shadow-md shadow-emerald-500/10'\\n                                : 'bg-gradient-to-r from-emerald-500/20 via-teal-500/20 to-emerald-600/20 hover:from-emerald-500 hover:to-emerald-400 text-emerald-400 hover:text-slate-950 border border-emerald-500/50 shadow-lg shadow-emerald-500/20 hover:shadow-emerald-500/40'\\n                            }`}\\n                          >\\n                            <FolderOpen className={`w-4 h-4 ${exportFolderName ? 'text-emerald-400' : 'text-emerald-300'}`} />\\n                            <span>\\n                              {exportFolderName \\n                                ? `📁 โฟลเดอร์ที่เลือก: ${exportFolderName}` \\n                                : '\n<truncated 169 bytes>",
  "TargetFile": "\"/Users/paulpolsulintaboon/Documents/GitHub/ContentFactory/frontend/src/App.tsx\""
}